libphoebe.cpython-312-x86_64-linux-gnu.so
phoebe-2.4.21.dist-info/METADATA
phoebe-2.4.21.dist-info/top_level.txt
phoebe-2.4.21.dist-info/WHEEL
phoebe-2.4.21.dist-info/RECORD
phoebe-2.4.21.dist-info/licenses/LICENSE.md
phoebe-2.4.21.data/scripts/phoebe-server
phoebe-2.4.21.data/scripts/phoebe-autofig
phoebe/__init__.py
phoebe/dynamics/nbody.py
phoebe/dynamics/__init__.py
phoebe/dynamics/keplerian.py
phoebe/helpers/__init__.py
phoebe/utils/__init__.py
phoebe/pool/multipool.py
phoebe/pool/pool.py
phoebe/pool/__init__.py
phoebe/pool/mpi.py
phoebe/pool/serial.py
phoebe/pool/error.py
phoebe/solverbackends/rv_geometry.py
phoebe/solverbackends/lc_geometry.py
phoebe/solverbackends/solverbackends.py
phoebe/solverbackends/__init__.py
phoebe/solverbackends/knn/detached.pf.knn
phoebe/solverbackends/knn/__init__.py
phoebe/solverbackends/knn/contact.2g.knn
phoebe/solverbackends/ebai/__init__.py
phoebe/solverbackends/ebai/bounds.data
phoebe/solverbackends/ebai/i2h.weights
phoebe/solverbackends/ebai/h2o.weights
phoebe/parameters/component.py
phoebe/parameters/system.py
phoebe/parameters/constraint.py
phoebe/parameters/dataset.py
phoebe/parameters/compute.py
phoebe/parameters/__init__.py
phoebe/parameters/twighelpers.py
phoebe/parameters/setting.py
phoebe/parameters/unit_choices.py
phoebe/parameters/hierarchy.py
phoebe/parameters/server.py
phoebe/parameters/feature.py
phoebe/parameters/parameters.py
phoebe/parameters/figure/dataset.py
phoebe/parameters/figure/__init__.py
phoebe/parameters/figure/solution.py
phoebe/parameters/figure/distribution.py
phoebe/parameters/figure/common.py
phoebe/parameters/solver/optimizer.py
phoebe/parameters/solver/sampler.py
phoebe/parameters/solver/__init__.py
phoebe/parameters/solver/estimator.py
phoebe/backend/mesh.py
phoebe/backend/eclipse.py
phoebe/backend/mesh_wd.py
phoebe/backend/backends.py
phoebe/backend/__init__.py
phoebe/backend/universe.py
phoebe/backend/oc_geometry.py
phoebe/backend/etvs.py
phoebe/backend/horizon_analytic.py
phoebe/algorithms/ceclipse.cpp
phoebe/algorithms/ceclipse.cpython-312-x86_64-linux-gnu.so
phoebe/algorithms/__init__.py
