Metadata-Version: 2.4
Name: phoebe
Version: 2.4.21
Summary: PHOEBE: modeling and analysis of eclipsing binary stars
Author-email: Andrej Prša <aprsa@villanova.edu>, Kyle Conroy <kyle.conroy@villanova.edu>, Angela Kochoska <angela.kochoska@villanova.edu>, Martin Horvat <martin.horvat@fmf.uni-lj.si>, Dave Jones <djones@iac.es>, Michael Abdul-Masih <michael.abdul-masih@eso.org>, Bert Pablo <hpablo@aavso.org>, Joe Giammarco <giammarc@eastern.edu>
Maintainer-email: Kyle Conroy <kyle.conroy@villanova.edu>, Andrej Prša <aprsa@villanova.edu>
License: GPL-3.0-or-later
Project-URL: homepage, https://phoebe-project.org
Project-URL: repository, https://github.com/phoebe-project/phoebe2
Project-URL: documentation, https://phoebe-project.org/docs
Keywords: phoebe,science,astronomy,astrophysics,binary stars,eclipsing binary stars
Classifier: Development Status :: 5 - Production/Stable
Classifier: Environment :: Console
Classifier: Intended Audience :: Education
Classifier: Intended Audience :: Science/Research
Classifier: License :: OSI Approved :: GNU General Public License v3 (GPLv3)
Classifier: Natural Language :: English
Classifier: Operating System :: POSIX :: Linux
Classifier: Operating System :: MacOS
Classifier: Programming Language :: Python :: 3
Classifier: Programming Language :: C
Classifier: Programming Language :: C++
Classifier: Topic :: Education
Classifier: Topic :: Scientific/Engineering :: Astronomy
Classifier: Topic :: Scientific/Engineering :: Physics
Classifier: Topic :: Scientific/Engineering :: Visualization
Classifier: Topic :: Software Development :: Libraries :: Python Modules
Classifier: Topic :: Software Development :: User Interfaces
Requires-Python: >=3.8
License-File: LICENSE.md
Requires-Dist: numpy
Requires-Dist: scipy
Requires-Dist: astropy
Requires-Dist: pytest
Requires-Dist: tqdm
Requires-Dist: corner
Requires-Dist: requests
Requires-Dist: python-socketio
Requires-Dist: flask
Requires-Dist: flask-cors
Requires-Dist: flask-socketio
Requires-Dist: gevent
Requires-Dist: gevent-websocket
Dynamic: license-file
